{
  "variant": {
    "choices": {
      "EnglishVariant": {
        "long": "select to build variant 'EnglishVariant'",
        "settings": {
          "VARIANT": "EnglishVariant"
        },
        "short": "EnglishVariant"
      },
      "GermanVariant": {
        "long": "select to build variant 'GermanVariant'",
        "settings": {
          "VARIANT": "GermanVariant"
        },
        "short": "GermanVariant"
      }
    },
    "default": "EnglishVariant"
  },
  "buildType": {
    "default": "Debug",
    "choices": {
      "Debug": {
        "short": "Debug",
        "long": "Disable optimizations and include debug information",
        "buildType": "Debug"
      },
      "Release": {
        "short": "Release",
        "long": "Optimize for speed and exclude debug information",
        "buildType": "Release"
      }
    }
  }
}
